qwiic/__init__.py
qwiic/drivers/pi_servo_hat/DESCRIPTION.rst
qwiic/drivers/pi_servo_hat/LICENSE
qwiic/drivers/pi_servo_hat/README.md
qwiic/drivers/pi_servo_hat/pi_servo_hat.py
qwiic/drivers/pi_servo_hat/setup.py
qwiic/drivers/pi_servo_hat/docs/Makefile
qwiic/drivers/pi_servo_hat/docs/apiref.rst
qwiic/drivers/pi_servo_hat/docs/conf.py
qwiic/drivers/pi_servo_hat/docs/ex1.rst
qwiic/drivers/pi_servo_hat/docs/ex2.rst
qwiic/drivers/pi_servo_hat/docs/ex3.rst
qwiic/drivers/pi_servo_hat/docs/ex4.rst
qwiic/drivers/pi_servo_hat/docs/index.rst
qwiic/drivers/pi_servo_hat/docs/make.bat
qwiic/drivers/pi_servo_hat/docs/requirements.txt
qwiic/drivers/pi_servo_hat/docs/_build/doctrees/apiref.doctree
qwiic/drivers/pi_servo_hat/docs/_build/doctrees/environment.pickle
qwiic/drivers/pi_servo_hat/docs/_build/doctrees/ex1.doctree
qwiic/drivers/pi_servo_hat/docs/_build/doctrees/ex2.doctree
qwiic/drivers/pi_servo_hat/docs/_build/doctrees/ex3.doctree
qwiic/drivers/pi_servo_hat/docs/_build/doctrees/ex4.doctree
qwiic/drivers/pi_servo_hat/docs/_build/doctrees/index.doctree
qwiic/drivers/pi_servo_hat/docs/_build/html/apiref.html
qwiic/drivers/pi_servo_hat/docs/_build/html/ex1.html
qwiic/drivers/pi_servo_hat/docs/_build/html/ex2.html
qwiic/drivers/pi_servo_hat/docs/_build/html/ex3.html
qwiic/drivers/pi_servo_hat/docs/_build/html/ex4.html
qwiic/drivers/pi_servo_hat/docs/_build/html/genindex.html
qwiic/drivers/pi_servo_hat/docs/_build/html/index.html
qwiic/drivers/pi_servo_hat/docs/_build/html/objects.inv
qwiic/drivers/pi_servo_hat/docs/_build/html/search.html
qwiic/drivers/pi_servo_hat/docs/_build/html/searchindex.js
qwiic/drivers/pi_servo_hat/docs/_build/html/_sources/apiref.rst.txt
qwiic/drivers/pi_servo_hat/docs/_build/html/_sources/ex1.rst.txt
qwiic/drivers/pi_servo_hat/docs/_build/html/_sources/ex2.rst.txt
qwiic/drivers/pi_servo_hat/docs/_build/html/_sources/ex3.rst.txt
qwiic/drivers/pi_servo_hat/docs/_build/html/_sources/ex4.rst.txt
qwiic/drivers/qwiic_otos/sparkfun_qwiic_otos.egg-info/PKG-INFO
qwiic/drivers/qwiic_otos/sparkfun_qwiic_otos.egg-info/SOURCES.txt
qwiic/drivers/qwiic_otos/sparkfun_qwiic_otos.egg-info/dependency_links.txt
qwiic/drivers/qwiic_otos/sparkfun_qwiic_otos.egg-info/requires.txt
qwiic/drivers/qwiic_otos/sparkfun_qwiic_otos.egg-info/top_level.txt
qwiic/drivers/qwiic_otos/sparkfun_qwiic_otos_py.egg-info/PKG-INFO
qwiic/drivers/qwiic_otos/sparkfun_qwiic_otos_py.egg-info/SOURCES.txt
qwiic/drivers/qwiic_otos/sparkfun_qwiic_otos_py.egg-info/dependency_links.txt
qwiic/drivers/qwiic_otos/sparkfun_qwiic_otos_py.egg-info/requires.txt
qwiic/drivers/qwiic_otos/sparkfun_qwiic_otos_py.egg-info/top_level.txt
sparkfun_qwiic-1.1.10.dist-info/LICENSE
sparkfun_qwiic-1.1.10.dist-info/METADATA
sparkfun_qwiic-1.1.10.dist-info/WHEEL
sparkfun_qwiic-1.1.10.dist-info/top_level.txt
sparkfun_qwiic-1.1.10.dist-info/RECORD
