Metadata-Version: 2.1
Name: sparkfun_qwiic
Version: 1.1.10
Summary: SparkFun Electronics qwiic library
Home-page: http://www.sparkfun.com/qwiic
Author: SparkFun Electronics
Author-email: info@sparkfun.com
License: MIT
Keywords: electronics,maker
Classifier: Development Status :: 5 - Production/Stable
Classifier: Intended Audience :: Developers
Classifier: Topic :: Software Development :: Build Tools
Classifier: License :: OSI Approved :: MIT License
Classifier: Programming Language :: Python :: 2.7
Classifier: Programming Language :: Python :: 3.5
Classifier: Programming Language :: Python :: 3.6
Classifier: Programming Language :: Python :: 3.7
License-File: LICENSE
Requires-Dist: sparkfun-qwiic-i2c
Requires-Dist: sparkfun-pi-servo-hat
Requires-Dist: sparkfun-qwiic-adxl313
Requires-Dist: sparkfun-qwiic-alphanumeric
Requires-Dist: sparkfun-qwiic-as6212
Requires-Dist: sparkfun-qwiic-bme280
Requires-Dist: sparkfun-qwiic-button
Requires-Dist: sparkfun-qwiic-ccs811
Requires-Dist: sparkfun-qwiic-dual-encoder-reader
Requires-Dist: sparkfun-qwiic-eeprom
Requires-Dist: sparkfun-qwiic-gpio
Requires-Dist: sparkfun-qwiic-icm20948
Requires-Dist: sparkfun-qwiic-joystick
Requires-Dist: sparkfun-qwiic-keypad
Requires-Dist: sparkfun-qwiic-kx13x
Requires-Dist: sparkfun-qwiic-large-oled
Requires-Dist: sparkfun-qwiic-led-stick
Requires-Dist: sparkfun-qwiic-max3010x
Requires-Dist: sparkfun-qwiic-micro-oled
Requires-Dist: sparkfun-qwiic-oled-base
Requires-Dist: sparkfun-qwiic-oled-display
Requires-Dist: sparkfun-qwiic-otos
Requires-Dist: sparkfun-qwiic-pca9685
Requires-Dist: sparkfun-qwiic-pir
Requires-Dist: sparkfun-qwiic-proximity
Requires-Dist: sparkfun-qwiic-relay
Requires-Dist: sparkfun-qwiic-rfid
Requires-Dist: sparkfun-qwiic-scmd
Requires-Dist: sparkfun-qwiic-serlcd
Requires-Dist: sparkfun-qwiic-sgp40
Requires-Dist: sparkfun-qwiic-soil-moisture-sensor
Requires-Dist: sparkfun-qwiic-tca9548a
Requires-Dist: sparkfun-qwiic-titan-gps
Requires-Dist: sparkfun-qwiic-twist
Requires-Dist: sparkfun-qwiic-vl53l1x
Requires-Dist: sparkfun-top-phat-button
Requires-Dist: sparkfun-ublox-gps
